DataProcX/__init__.py
DataProcX/data.py
DataProcX/parser.py
DataProcX/util.py
DataProcX-0.1.4.dist-info/LICENSE
DataProcX-0.1.4.dist-info/METADATA
DataProcX-0.1.4.dist-info/WHEEL
DataProcX-0.1.4.dist-info/top_level.txt
DataProcX-0.1.4.dist-info/RECORD
