Metadata-Version: 2.1
Name: DataProcX
Version: 0.1.4
Summary: Text label processing framework.
Home-page: https://github.com/FrostMiKu/DataProc
Author: Lethon
Author-email: 1134505018@qq.com
License: GPL-3.0 License
Platform: UNKNOWN
Classifier: License :: OSI Approved :: GNU General Public License v3 (GPLv3)
Classifier: Programming Language :: Python
Classifier: Programming Language :: Python :: 3
Classifier: Programming Language :: Python :: 3.6
Classifier: Programming Language :: Python :: Implementation :: CPython
Classifier: Programming Language :: Python :: Implementation :: PyPy
Requires-Python: >=3.6.0
License-File: LICENSE
Requires-Dist: numpy
